Metadata-Version: 2.1
Name: antdingopensdk
Version: 0.0.9
Summary: alipay ant ding open sdk for python
Home-page: UNKNOWN
Author: alipay ant ding open
License: UNKNOWN
Platform: UNKNOWN
Requires-Python: >=3.6
License-File: LICENSE
